renamer.py
renamer_cli-1.2.2.dist-info/LICENSE
renamer_cli-1.2.2.dist-info/METADATA
renamer_cli-1.2.2.dist-info/WHEEL
renamer_cli-1.2.2.dist-info/entry_points.txt
renamer_cli-1.2.2.dist-info/top_level.txt
renamer_cli-1.2.2.dist-info/RECORD
