Metadata-Version: 2.1
Name: renamer-cli
Version: 1.2.2
Summary: A command-line tool for fast and flexible file and directory renaming.
Home-page: https://github.com/READMEmaybe/renamer-cli
Author: READMEmaybe
Author-email: READMEmaybe@protonmail.com
License: MIT
Platform: UNKNOWN
Classifier: Programming Language :: Python :: 3
Classifier: License :: OSI Approved :: MIT License
License-File: LICENSE
